rapidfireai/__init__.py
rapidfireai/cli.py
rapidfireai/experiment.py
rapidfireai/version.py
rapidfireai/evals/__init__.py
rapidfireai/evals/actors/__init__.py
rapidfireai/evals/actors/doc_actor.py
rapidfireai/evals/actors/inference_engines.py
rapidfireai/evals/actors/query_actor.py
rapidfireai/evals/actors/rate_limiter_actor.py
rapidfireai/evals/automl/__init__.py
rapidfireai/evals/automl/base.py
rapidfireai/evals/automl/datatypes.py
rapidfireai/evals/automl/grid_search.py
rapidfireai/evals/automl/model_config.py
rapidfireai/evals/automl/random_search.py
rapidfireai/evals/data/__init__.py
rapidfireai/evals/data/dataset.py
rapidfireai/evals/db/__init__.py
rapidfireai/evals/db/db_interface.py
rapidfireai/evals/db/rf_db.py
rapidfireai/evals/db/tables.sql
rapidfireai/evals/dispatcher/__init__.py
rapidfireai/evals/dispatcher/dispatcher.py
rapidfireai/evals/metrics/__init__.py
rapidfireai/evals/metrics/aggregator.py
rapidfireai/evals/metrics/online_strategies.py
rapidfireai/evals/rag/__init__.py
rapidfireai/evals/rag/prompt_manager.py
rapidfireai/evals/rag/rag_pipeline.py
rapidfireai/evals/scheduling/__init__.py
rapidfireai/evals/scheduling/controller.py
rapidfireai/evals/scheduling/interactive_control.py
rapidfireai/evals/scheduling/pipeline_scheduler.py
rapidfireai/evals/scheduling/scheduler.py
rapidfireai/evals/utils/__init__.py
rapidfireai/evals/utils/automl_utils.py
rapidfireai/evals/utils/constants.py
rapidfireai/evals/utils/error_utils.py
rapidfireai/evals/utils/experiment_utils.py
rapidfireai/evals/utils/inference_configs.py
rapidfireai/evals/utils/logger.py
rapidfireai/evals/utils/notebook_ui.py
rapidfireai/evals/utils/progress_display.py
rapidfireai/evals/utils/ratelimiter.py
rapidfireai/evals/utils/serialize.py
rapidfireai/fit/automl/__init__.py
rapidfireai/fit/automl/base.py
rapidfireai/fit/automl/datatypes.py
rapidfireai/fit/automl/grid_search.py
rapidfireai/fit/automl/model_config.py
rapidfireai/fit/automl/random_search.py
rapidfireai-0.12.8.dist-info/licenses/LICENSE
rapidfireai-0.12.8.dist-info/METADATA
rapidfireai-0.12.8.dist-info/WHEEL
rapidfireai-0.12.8.dist-info/entry_points.txt
rapidfireai-0.12.8.dist-info/top_level.txt
rapidfireai-0.12.8.dist-info/RECORD
