Metadata-Version: 2.4
Name: rapidfireai
Version: 0.12.8
Summary: RapidFire AI: Rapid experimentation for easier, faster, and more impactful AI customization. Built for agentic RAG, context engineering, fine-tuning, and post-training of LLMs and other DL models. 
Author-email: "RapidFire AI Inc." <support@rapidfire.ai>
License: Apache-2.0
Project-URL: Homepage, https://rapidfire.ai
Project-URL: Documentation, https://oss-docs.rapidfire.ai
Project-URL: Repository, https://github.com/RapidFireAI/rapidfireai
Keywords: ai,rapidfire,rapidfireai,llm,deep-learning,artificial-intelligence,machine-learning,mlflow,experiment-tracking,fine-tuning,post-training,rag,context-engineering
Classifier: Development Status :: 4 - Beta
Classifier: Intended Audience :: Developers
Classifier: Intended Audience :: Science/Research
Classifier: License :: OSI Approved :: Apache Software License
Classifier: Operating System :: OS Independent
Classifier: Programming Language :: Python :: 3
Classifier: Programming Language :: Python :: 3.12
Classifier: Topic :: Scientific/Engineering :: Artificial Intelligence
Classifier: Topic :: Software Development :: Libraries :: Python Modules
Classifier: Topic :: Software Development :: Libraries :: Application Frameworks
Requires-Python: >=3.12
License-File: LICENSE
Requires-Dist: flask>=3.1.1
Requires-Dist: flask-cors>=6.0.1
Requires-Dist: waitress>=3.0.2
Requires-Dist: jq>=1.10.0
Requires-Dist: dill<0.3.9,>=0.3.0
Requires-Dist: jedi>=0.16
Requires-Dist: uv>=0.8.14
Provides-Extra: colab-evals
Requires-Dist: sentence-transformers>=5.1.0; extra == "colab-evals"
Requires-Dist: ray>=2.44.1; extra == "colab-evals"
Requires-Dist: transformers>=4.56.1; extra == "colab-evals"
Requires-Dist: openai>=1.106.1; extra == "colab-evals"
Requires-Dist: tiktoken>=0.11.0; extra == "colab-evals"
Requires-Dist: langchain; extra == "colab-evals"
Requires-Dist: langchain-classic; extra == "colab-evals"
Requires-Dist: langchain-core; extra == "colab-evals"
Requires-Dist: langchain-community; extra == "colab-evals"
Requires-Dist: langchain-openai; extra == "colab-evals"
Requires-Dist: langchain-huggingface; extra == "colab-evals"
Requires-Dist: unstructured>=0.18.15; extra == "colab-evals"
Provides-Extra: colab-fit
Requires-Dist: pandas<2.3.0,>=2.0.0; extra == "colab-fit"
Requires-Dist: psutil>=5.9.0; extra == "colab-fit"
Requires-Dist: torch>=2.8.0; extra == "colab-fit"
Requires-Dist: transformers>=4.55.2; extra == "colab-fit"
Requires-Dist: peft>=0.17.0; extra == "colab-fit"
Requires-Dist: trl==0.21.0; extra == "colab-fit"
Requires-Dist: bitsandbytes>=0.47.0; extra == "colab-fit"
Requires-Dist: nltk>=3.9.1; extra == "colab-fit"
Requires-Dist: evaluate>=0.4.5; extra == "colab-fit"
Requires-Dist: rouge-score>=0.1.2; extra == "colab-fit"
Requires-Dist: sentencepiece>=0.2.1; extra == "colab-fit"
Requires-Dist: mlflow>=3.2.0; extra == "colab-fit"
Requires-Dist: requests>=2.32.0; extra == "colab-fit"
Requires-Dist: loguru>=0.7.3; extra == "colab-fit"
Requires-Dist: ipython>=7.34.0; extra == "colab-fit"
Requires-Dist: jupyter>=1.1.1; extra == "colab-fit"
Requires-Dist: ipywidgets<9.0.0,>=7.3.4; extra == "colab-fit"
Requires-Dist: tensorboard>=2.11.0; extra == "colab-fit"
Provides-Extra: local-evals
Requires-Dist: torch==2.5.1; extra == "local-evals"
Requires-Dist: torchvision==0.20.1; extra == "local-evals"
Requires-Dist: torchaudio==2.5.1; extra == "local-evals"
Requires-Dist: datasets==3.6.0; extra == "local-evals"
Requires-Dist: sentence-transformers==5.1.0; extra == "local-evals"
Requires-Dist: gpustat==1.1.1; extra == "local-evals"
Requires-Dist: ray==2.44.1; extra == "local-evals"
Requires-Dist: transformers==4.56.1; extra == "local-evals"
Requires-Dist: vllm==0.7.2; extra == "local-evals"
Requires-Dist: openai==1.106.1; extra == "local-evals"
Requires-Dist: tiktoken==0.11.0; extra == "local-evals"
Requires-Dist: langchain; extra == "local-evals"
Requires-Dist: langchain-classic; extra == "local-evals"
Requires-Dist: langchain-core; extra == "local-evals"
Requires-Dist: langchain-community; extra == "local-evals"
Requires-Dist: langchain-openai; extra == "local-evals"
Requires-Dist: langchain-huggingface; extra == "local-evals"
Requires-Dist: faiss-gpu-cu12==1.12.0; extra == "local-evals"
Requires-Dist: scipy==1.16.1; extra == "local-evals"
Requires-Dist: pandas==2.3.2; extra == "local-evals"
Requires-Dist: pyarrow==21.0.0; extra == "local-evals"
Requires-Dist: numpy==1.26.4; extra == "local-evals"
Requires-Dist: unstructured==0.18.15; extra == "local-evals"
Requires-Dist: ipykernel==6.30.1; extra == "local-evals"
Requires-Dist: ipywidgets<9.0.0,>=7.3.4; extra == "local-evals"
Requires-Dist: tensorboard>=2.11.0; extra == "local-evals"
Requires-Dist: psutil==7.0.0; extra == "local-evals"
Requires-Dist: tqdm==4.67.1; extra == "local-evals"
Requires-Dist: typing-extensions>=4.0.0; extra == "local-evals"
Requires-Dist: peft>=0.17.0; extra == "local-evals"
Requires-Dist: trl==0.21.0; extra == "local-evals"
Requires-Dist: bitsandbytes>=0.47.0; extra == "local-evals"
Requires-Dist: nltk>=3.9.1; extra == "local-evals"
Requires-Dist: evaluate>=0.4.5; extra == "local-evals"
Requires-Dist: rouge-score>=0.1.2; extra == "local-evals"
Requires-Dist: sentencepiece>=0.2.1; extra == "local-evals"
Requires-Dist: mlflow>=3.2.0; extra == "local-evals"
Requires-Dist: requests>=2.32.0; extra == "local-evals"
Requires-Dist: loguru>=0.7.3; extra == "local-evals"
Requires-Dist: ipython>=7.34.0; extra == "local-evals"
Requires-Dist: jupyter>=1.1.1; extra == "local-evals"
Requires-Dist: flashinfer-python==0.2.5; extra == "local-evals"
Provides-Extra: local-fit
Requires-Dist: torch>=2.7.0; extra == "local-fit"
Requires-Dist: torchvision>=0.22.0; extra == "local-fit"
Requires-Dist: torchaudio>=2.7.0; extra == "local-fit"
Requires-Dist: datasets==3.6.0; extra == "local-fit"
Requires-Dist: sentence-transformers==5.1.0; extra == "local-fit"
Requires-Dist: gpustat==1.1.1; extra == "local-fit"
Requires-Dist: ray==2.44.1; extra == "local-fit"
Requires-Dist: transformers>=4.57.1; extra == "local-fit"
Requires-Dist: openai==1.106.1; extra == "local-fit"
Requires-Dist: tiktoken==0.11.0; extra == "local-fit"
Requires-Dist: langchain; extra == "local-fit"
Requires-Dist: langchain-classic; extra == "local-fit"
Requires-Dist: langchain-core; extra == "local-fit"
Requires-Dist: langchain-community; extra == "local-fit"
Requires-Dist: langchain-openai; extra == "local-fit"
Requires-Dist: langchain-huggingface; extra == "local-fit"
Requires-Dist: faiss-gpu-cu12==1.12.0; extra == "local-fit"
Requires-Dist: scipy==1.16.1; extra == "local-fit"
Requires-Dist: pandas==2.3.2; extra == "local-fit"
Requires-Dist: pyarrow==21.0.0; extra == "local-fit"
Requires-Dist: numpy==1.26.4; extra == "local-fit"
Requires-Dist: unstructured==0.18.15; extra == "local-fit"
Requires-Dist: ipykernel==6.30.1; extra == "local-fit"
Requires-Dist: ipywidgets<9.0.0,>=7.3.4; extra == "local-fit"
Requires-Dist: tensorboard>=2.11.0; extra == "local-fit"
Requires-Dist: psutil==7.0.0; extra == "local-fit"
Requires-Dist: tqdm==4.67.1; extra == "local-fit"
Requires-Dist: typing-extensions>=4.0.0; extra == "local-fit"
Requires-Dist: peft>=0.17.0; extra == "local-fit"
Requires-Dist: trl==0.21.0; extra == "local-fit"
Requires-Dist: bitsandbytes>=0.47.0; extra == "local-fit"
Requires-Dist: nltk>=3.9.1; extra == "local-fit"
Requires-Dist: evaluate>=0.4.5; extra == "local-fit"
Requires-Dist: rouge-score>=0.1.2; extra == "local-fit"
Requires-Dist: sentencepiece>=0.2.1; extra == "local-fit"
Requires-Dist: dill>=0.3.8; extra == "local-fit"
Requires-Dist: mlflow>=3.2.0; extra == "local-fit"
Requires-Dist: requests>=2.32.0; extra == "local-fit"
Requires-Dist: loguru>=0.7.3; extra == "local-fit"
Requires-Dist: ipython>=7.34.0; extra == "local-fit"
Requires-Dist: jupyter>=1.1.1; extra == "local-fit"
Dynamic: license-file
